vkbottle_sync/__init__.py
vkbottle_sync-0.1.dist-info/WHEEL
vkbottle_sync-0.1.dist-info/METADATA
vkbottle_sync-0.1.dist-info/RECORD
